README.rst
setup.py
ask_so.egg-info/PKG-INFO
ask_so.egg-info/SOURCES.txt
ask_so.egg-info/dependency_links.txt
ask_so.egg-info/entry_points.txt
ask_so.egg-info/pbr.json
ask_so.egg-info/requires.txt
ask_so.egg-info/top_level.txt
askso/__init__.py
askso/__main__.py
askso/execute.py
askso/files.py
askso/server.py
askso/utils.py
askso/static/index.html
askso/static/main.js