Metadata-Version: 1.1
Name: ask-so
Version: 1.0.4
Summary: AskSO - StackOverflow Python Question Assistant
Home-page: https://github.com/alexmojaki/askso
Author: Alex Hall
Author-email: alex.mojaki@gmail.com
License: MIT (Expat)
Platform: UNKNOWN
Classifier: License :: OSI Approved :: MIT License
Classifier: Programming Language :: Python
Classifier: Programming Language :: Python :: 2
Classifier: Programming Language :: Python :: 2.6
Classifier: Programming Language :: Python :: 2.7
Classifier: Programming Language :: Python :: 3
Classifier: Programming Language :: Python :: 3.3
Classifier: Programming Language :: Python :: 3.4
Classifier: Programming Language :: Python :: 3.5
